canvasdraw/__init__.py
canvasdraw/parser.py
canvasdraw-0.0.4.dist-info/METADATA
canvasdraw-0.0.4.dist-info/WHEEL
canvasdraw-0.0.4.dist-info/licenses/LICENSE
canvasdraw-0.0.4.dist-info/RECORD
