Metadata-Version: 2.3
Name: canvasdraw
Version: 0.0.4
Summary: A parser for easier generating of drawings for the JavaScript Canvas API
Project-URL: Homepage, https://github.com/twboom/CanvasDraw
Project-URL: Bug Tracker, https://github.com/twboom/CanvasDraw/issues
Author-email: Thijs Boom <thijs@twboom.dev>
Classifier: License :: OSI Approved :: GNU General Public License v3 (GPLv3)
Classifier: Operating System :: OS Independent
Classifier: Programming Language :: Python :: 3
Requires-Python: >=3.7
